test/__init__.py
test/test_imports.py
test/test_serialise.py
test/personalization_agent/__init__.py
test/personalization_agent/test_personalization_agent.py
test/personalization_agent/test_query.py
test/query_agent/test_query_model.py
test/transformation_agent/test_transformation_model.py
weaviate_agents/__init__.py
weaviate_agents/base.py
weaviate_agents/py.typed
weaviate_agents/serialise.py
weaviate_agents/utils.py
weaviate_agents/classes/__init__.py
weaviate_agents/classes/core.py
weaviate_agents/classes/personalization.py
weaviate_agents/classes/query.py
weaviate_agents/classes/transformation.py
weaviate_agents/personalization/__init__.py
weaviate_agents/personalization/personalization_agent.py
weaviate_agents/personalization/query.py
weaviate_agents/personalization/classes/__init__.py
weaviate_agents/personalization/classes/persona.py
weaviate_agents/personalization/classes/query.py
weaviate_agents/personalization/classes/request.py
weaviate_agents/personalization/classes/response.py
weaviate_agents/query/.gitkeep
weaviate_agents/query/__init__.py
weaviate_agents/query/query_agent.py
weaviate_agents/query/search.py
weaviate_agents/query/classes/__init__.py
weaviate_agents/query/classes/collection.py
weaviate_agents/query/classes/request.py
weaviate_agents/query/classes/response.py
weaviate_agents/transformation/.gitkeep
weaviate_agents/transformation/__init__.py
weaviate_agents/transformation/transformation_agent.py
weaviate_agents/transformation/classes/__init__.py
weaviate_agents/transformation/classes/operation.py
weaviate_agents-1.2.0.dist-info/METADATA
weaviate_agents-1.2.0.dist-info/WHEEL
weaviate_agents-1.2.0.dist-info/top_level.txt
weaviate_agents-1.2.0.dist-info/RECORD
