Metadata-Version: 2.4
Name: weaviate-agents
Version: 1.2.0
Summary: The official sub-package for the Weaviate Agents project.
Requires-Python: >=3.9
Requires-Dist: httpx-sse>=0.4.0
Requires-Dist: rich>=13.9.4
Requires-Dist: weaviate-client>=4.11.0
